drf_yasg2/__init__.py
drf_yasg2/app_settings.py
drf_yasg2/apps.py
drf_yasg2/codecs.py
drf_yasg2/errors.py
drf_yasg2/generators.py
drf_yasg2/middleware.py
drf_yasg2/openapi.py
drf_yasg2/renderers.py
drf_yasg2/utils.py
drf_yasg2/views.py
drf_yasg2/inspectors/__init__.py
drf_yasg2/inspectors/base.py
drf_yasg2/inspectors/field.py
drf_yasg2/inspectors/query.py
drf_yasg2/inspectors/view.py
drf_yasg2/management/__init__.py
drf_yasg2/management/commands/__init__.py
drf_yasg2/management/commands/generate_swagger.py
drf_yasg2/static/drf_yasg2/__init__.py
drf_yasg2/static/drf_yasg2/immutable.min.js
drf_yasg2/static/drf_yasg2/insQ.min.js
drf_yasg2/static/drf_yasg2/redoc-init.js
drf_yasg2/static/drf_yasg2/style.css
drf_yasg2/static/drf_yasg2/swagger-ui-init.js
drf_yasg2/static/drf_yasg2/url-polyfill.min.js
drf_yasg2/static/drf_yasg2/redoc/redoc-logo.png
drf_yasg2/static/drf_yasg2/redoc/redoc.min.js
drf_yasg2/static/drf_yasg2/redoc-old/redoc.min.js
drf_yasg2/static/drf_yasg2/swagger-ui-dist/absolute-path.js
drf_yasg2/static/drf_yasg2/swagger-ui-dist/favicon-32x32.png
drf_yasg2/static/drf_yasg2/swagger-ui-dist/index.js
drf_yasg2/static/drf_yasg2/swagger-ui-dist/oauth2-redirect.html
drf_yasg2/static/drf_yasg2/swagger-ui-dist/swagger-ui-bundle.js
drf_yasg2/static/drf_yasg2/swagger-ui-dist/swagger-ui-es-bundle-core.js
drf_yasg2/static/drf_yasg2/swagger-ui-dist/swagger-ui-es-bundle.js
drf_yasg2/static/drf_yasg2/swagger-ui-dist/swagger-ui-standalone-preset.js
drf_yasg2/static/drf_yasg2/swagger-ui-dist/swagger-ui.css
drf_yasg2/templates/drf_yasg2/redoc-old.html
drf_yasg2/templates/drf_yasg2/redoc.html
drf_yasg2/templates/drf_yasg2/swagger-ui.html
drf_yasg2-1.19.4.dist-info/LICENSE.md
drf_yasg2-1.19.4.dist-info/METADATA
drf_yasg2-1.19.4.dist-info/WHEEL
drf_yasg2-1.19.4.dist-info/top_level.txt
drf_yasg2-1.19.4.dist-info/RECORD
