Metadata-Version: 2.1
Name: drf-yasg2
Version: 1.19.4
Summary: Automated generation of real Swagger/OpenAPI 2.0 schemas from Django Rest Framework code
Home-page: https://github.com/JoelLefkowitz/drf-yasg
Author: Joel Lefkowitz
Author-email: joellefkowitz@hotmail.com
License: UNKNOWN
Keywords: schema,swagger,openapi,codegen,documentation,django,django-rest-framework
Platform: UNKNOWN
Classifier: Intended Audience :: Developers
Classifier: License :: OSI Approved :: BSD License
Classifier: Development Status :: 5 - Production/Stable
Classifier: Operating System :: OS Independent
Classifier: Environment :: Web Environment
Classifier: Programming Language :: Python :: 3.6
Classifier: Programming Language :: Python :: 3.7
Classifier: Programming Language :: Python :: 3.8
Classifier: Programming Language :: Python :: 3.9
Classifier: Framework :: Django :: 2.2
Classifier: Framework :: Django :: 3.0
Classifier: Framework :: Django :: 3.1
Classifier: Topic :: Documentation
Classifier: Topic :: Software Development :: Code Generators
Provides-Extra: lint
Provides-Extra: format
Provides-Extra: dist
Provides-Extra: validation
Provides-Extra: docs
Provides-Extra: tests
Provides-Extra: heroku
